[
  {
    "timestamp": "2025-09-02T17:00:29.505+00:00",
    "sourceId": 12,
    "sequenceNo": 38865,
    "sizeBytes": 1400
  },
  {
    "timestamp": "2025-09-02T17:00:30.385+00:00",
    "sourceId": 12,
    "sequenceNo": 38866,
    "sizeBytes": 1400
  },
  {
    "timestamp": "2025-09-02T17:00:31.009+00:00",
    "sourceId": 12,
    "sequenceNo": 38867,
    "sizeBytes": 1400
  },
  {
    "timestamp": "2025-09-02T17:00:31.773+00:00",
    "sourceId": 12,
    "sequenceNo": 38868,
    "sizeBytes": 1400
  },
  {
    "timestamp": "2025-09-02T17:00:32.805+00:00",
    "sourceId": 12,
    "sequenceNo": 38869,
    "sizeBytes": 1400
  },
  {
    "timestamp": "2025-09-02T17:00:33.542+00:00",
    "sourceId": 12,
    "sequenceNo": 38870,
    "sizeBytes": 1400
  },
  {
    "timestamp": "2025-09-02T17:00:34.251+00:00",
    "sourceId": 12,
    "sequenceNo": 38871,
    "sizeBytes": 1400
  },
  {
    "timestamp": "2025-09-02T17:00:34.577+00:00",
    "sourceId": 12,
    "sequenceNo": 38872,
    "sizeBytes": 1400
  },
  {
    "timestamp": "2025-09-02T17:00:35.366+00:00",
    "sourceId": 12,
    "sequenceNo": 38873,
    "sizeBytes": 1400
  },
  {
    "timestamp": "2025-09-02T17:00:36.187+00:00",
    "sourceId": 12,
    "sequenceNo": 38874,
    "sizeBytes": 1400
  },
  {
    "timestamp": "2025-09-02T17:00:36.675+00:00",
    "sourceId": 12,
    "sequenceNo": 38875,
    "sizeBytes": 1400
  },
  {
    "timestamp": "2025-09-02T17:00:37.134+00:00",
    "sourceId": 12,
    "sequenceNo": 38876,
    "sizeBytes": 1400
  },
  {
    "timestamp": "2025-09-02T17:00:37.610+00:00",
    "sourceId": 12,
    "sequenceNo": 38877,
    "sizeBytes": 1400
  },
  {
    "timestamp": "2025-09-02T17:00:38.238+00:00",
    "sourceId": 12,
    "sequenceNo": 38878,
    "sizeBytes": 1400
  },
  {
    "timestamp": "2025-09-02T17:00:38.910+00:00",
    "sourceId": 12,
    "sequenceNo": 38879,
    "sizeBytes": 1400
  },
  {
    "timestamp": "2025-09-02T17:00:39.871+00:00",
    "sourceId": 12,
    "sequenceNo": 38880,
    "sizeBytes": 1400
  },
  {
    "timestamp": "2025-09-02T17:00:40.784+00:00",
    "sourceId": 12,
    "sequenceNo": 38881,
    "sizeBytes": 1400
  },
  {
    "timestamp": "2025-09-02T17:00:41.487+00:00",
    "sourceId": 12,
    "sequenceNo": 38882,
    "sizeBytes": 1400
  },
  {
    "timestamp": "2025-09-02T17:00:42.104+00:00",
    "sourceId": 12,
    "sequenceNo": 38883,
    "sizeBytes": 1400
  },
  {
    "timestamp": "2025-09-02T17:00:42.909+00:00",
    "sourceId": 12,
    "sequenceNo": 38884,
    "sizeBytes": 1400
  },
  {
    "timestamp": "2025-09-02T17:00:43.656+00:00",
    "sourceId": 12,
    "sequenceNo": 38885,
    "sizeBytes": 1400
  },
  {
    "timestamp": "2025-09-02T17:00:44.232+00:00",
    "sourceId": 12,
    "sequenceNo": 38886,
    "sizeBytes": 1400
  },
  {
    "timestamp": "2025-09-02T17:00:45.064+00:00",
    "sourceId": 12,
    "sequenceNo": 38887,
    "sizeBytes": 1400
  },
  {
    "timestamp": "2025-09-02T17:00:45.779+00:00",
    "sourceId": 12,
    "sequenceNo": 38888,
    "sizeBytes": 1400
  },
  {
    "timestamp": "2025-09-02T17:00:46.493+00:00",
    "sourceId": 12,
    "sequenceNo": 38889,
    "sizeBytes": 1400
  },
  {
    "timestamp": "2025-09-02T17:00:47.370+00:00",
    "sourceId": 12,
    "sequenceNo": 38890,
    "sizeBytes": 1400
  },
  {
    "timestamp": "2025-09-02T17:00:48.008+00:00",
    "sourceId": 12,
    "sequenceNo": 38891,
    "sizeBytes": 1400
  },
  {
    "timestamp": "2025-09-02T17:00:48.467+00:00",
    "sourceId": 12,
    "sequenceNo": 38892,
    "sizeBytes": 1400
  },
  {
    "timestamp": "2025-09-02T17:00:49.154+00:00",
    "sourceId": 12,
    "sequenceNo": 38893,
    "sizeBytes": 1400
  },
  {
    "timestamp": "2025-09-02T17:00:49.779+00:00",
    "sourceId": 12,
    "sequenceNo": 38894,
    "sizeBytes": 1400
  },
  {
    "timestamp": "2025-09-02T17:00:50.290+00:00",
    "sourceId": 12,
    "sequenceNo": 38895,
    "sizeBytes": 1400
  },
  {
    "timestamp": "2025-09-02T17:00:50.907+00:00",
    "sourceId": 12,
    "sequenceNo": 38896,
    "sizeBytes": 1400
  },
  {
    "timestamp": "2025-09-02T17:00:51.641+00:00",
    "sourceId": 12,
    "sequenceNo": 38897,
    "sizeBytes": 1400
  },
  {
    "timestamp": "2025-09-02T17:00:52.376+00:00",
    "sourceId": 12,
    "sequenceNo": 38898,
    "sizeBytes": 1400
  },
  {
    "timestamp": "2025-09-02T17:00:52.811+00:00",
    "sourceId": 12,
    "sequenceNo": 38899,
    "sizeBytes": 1400
  },
  {
    "timestamp": "2025-09-02T17:00:53.273+00:00",
    "sourceId": 12,
    "sequenceNo": 38900,
    "sizeBytes": 1400
  },
  {
    "timestamp": "2025-09-02T17:00:54.191+00:00",
    "sourceId": 12,
    "sequenceNo": 38901,
    "sizeBytes": 1400
  },
  {
    "timestamp": "2025-09-02T17:00:54.661+00:00",
    "sourceId": 12,
    "sequenceNo": 38902,
    "sizeBytes": 1400
  },
  {
    "timestamp": "2025-09-02T17:00:55.298+00:00",
    "sourceId": 12,
    "sequenceNo": 38903,
    "sizeBytes": 1400
  },
  {
    "timestamp": "2025-09-02T17:00:55.975+00:00",
    "sourceId": 12,
    "sequenceNo": 38904,
    "sizeBytes": 1400
  },
  {
    "timestamp": "2025-09-02T17:00:56.842+00:00",
    "sourceId": 12,
    "sequenceNo": 38905,
    "sizeBytes": 1400
  },
  {
    "timestamp": "2025-09-02T17:00:57.555+00:00",
    "sourceId": 12,
    "sequenceNo": 38906,
    "sizeBytes": 1400
  },
  {
    "timestamp": "2025-09-02T17:00:58.326+00:00",
    "sourceId": 12,
    "sequenceNo": 38907,
    "sizeBytes": 1400
  },
  {
    "timestamp": "2025-09-02T17:00:59.147+00:00",
    "sourceId": 12,
    "sequenceNo": 38908,
    "sizeBytes": 1400
  },
  {
    "timestamp": "2025-09-02T17:01:00.006+00:00",
    "sourceId": 12,
    "sequenceNo": 38909,
    "sizeBytes": 1400
  },
  {
    "timestamp": "2025-09-02T17:01:00.912+00:00",
    "sourceId": 12,
    "sequenceNo": 38910,
    "sizeBytes": 1400
  },
  {
    "timestamp": "2025-09-02T17:01:01.549+00:00",
    "sourceId": 12,
    "sequenceNo": 38911,
    "sizeBytes": 1400
  },
  {
    "timestamp": "2025-09-02T17:01:02.372+00:00",
    "sourceId": 12,
    "sequenceNo": 38912,
    "sizeBytes": 1400
  },
  {
    "timestamp": "2025-09-02T17:01:03.335+00:00",
    "sourceId": 12,
    "sequenceNo": 38913,
    "sizeBytes": 1400
  },
  {
    "timestamp": "2025-09-02T17:01:03.939+00:00",
    "sourceId": 12,
    "sequenceNo": 38914,
    "sizeBytes": 1400
  },
  {
    "timestamp": "2025-09-02T17:01:04.337+00:00",
    "sourceId": 12,
    "sequenceNo": 38915,
    "sizeBytes": 1400
  },
  {
    "timestamp": "2025-09-02T17:01:05.307+00:00",
    "sourceId": 12,
    "sequenceNo": 38916,
    "sizeBytes": 1400
  },
  {
    "timestamp": "2025-09-02T17:01:06.218+00:00",
    "sourceId": 12,
    "sequenceNo": 38917,
    "sizeBytes": 1400
  },
  {
    "timestamp": "2025-09-02T17:01:06.952+00:00",
    "sourceId": 12,
    "sequenceNo": 38918,
    "sizeBytes": 1400
  },
  {
    "timestamp": "2025-09-02T17:01:07.780+00:00",
    "sourceId": 12,
    "sequenceNo": 38919,
    "sizeBytes": 1400
  },
  {
    "timestamp": "2025-09-02T17:01:08.612+00:00",
    "sourceId": 12,
    "sequenceNo": 38920,
    "sizeBytes": 1400
  },
  {
    "timestamp": "2025-09-02T17:01:09.373+00:00",
    "sourceId": 12,
    "sequenceNo": 38921,
    "sizeBytes": 1400
  },
  {
    "timestamp": "2025-09-02T17:01:10.306+00:00",
    "sourceId": 12,
    "sequenceNo": 38922,
    "sizeBytes": 1400
  },
  {
    "timestamp": "2025-09-02T17:01:11.113+00:00",
    "sourceId": 12,
    "sequenceNo": 38923,
    "sizeBytes": 1400
  },
  {
    "timestamp": "2025-09-02T17:01:11.959+00:00",
    "sourceId": 12,
    "sequenceNo": 38924,
    "sizeBytes": 1400
  },
  {
    "timestamp": "2025-09-02T17:01:12.733+00:00",
    "sourceId": 12,
    "sequenceNo": 38925,
    "sizeBytes": 1400
  },
  {
    "timestamp": "2025-09-02T17:01:13.623+00:00",
    "sourceId": 12,
    "sequenceNo": 38926,
    "sizeBytes": 1400
  },
  {
    "timestamp": "2025-09-02T17:01:14.457+00:00",
    "sourceId": 12,
    "sequenceNo": 38927,
    "sizeBytes": 1400
  },
  {
    "timestamp": "2025-09-02T17:01:15.295+00:00",
    "sourceId": 12,
    "sequenceNo": 38928,
    "sizeBytes": 1400
  },
  {
    "timestamp": "2025-09-02T17:01:15.972+00:00",
    "sourceId": 12,
    "sequenceNo": 38929,
    "sizeBytes": 1400
  },
  {
    "timestamp": "2025-09-02T17:01:16.763+00:00",
    "sourceId": 12,
    "sequenceNo": 38930,
    "sizeBytes": 1400
  },
  {
    "timestamp": "2025-09-02T17:01:17.305+00:00",
    "sourceId": 12,
    "sequenceNo": 38931,
    "sizeBytes": 1400
  },
  {
    "timestamp": "2025-09-02T17:01:17.991+00:00",
    "sourceId": 12,
    "sequenceNo": 38932,
    "sizeBytes": 1400
  },
  {
    "timestamp": "2025-09-02T17:01:18.894+00:00",
    "sourceId": 12,
    "sequenceNo": 38933,
    "sizeBytes": 1400
  },
  {
    "timestamp": "2025-09-02T17:01:19.668+00:00",
    "sourceId": 12,
    "sequenceNo": 38934,
    "sizeBytes": 1400
  },
  {
    "timestamp": "2025-09-02T17:01:20.340+00:00",
    "sourceId": 12,
    "sequenceNo": 38935,
    "sizeBytes": 1400
  },
  {
    "timestamp": "2025-09-02T17:01:20.991+00:00",
    "sourceId": 12,
    "sequenceNo": 38936,
    "sizeBytes": 1400
  },
  {
    "timestamp": "2025-09-02T17:01:21.677+00:00",
    "sourceId": 12,
    "sequenceNo": 38937,
    "sizeBytes": 1400
  },
  {
    "timestamp": "2025-09-02T17:01:22.594+00:00",
    "sourceId": 12,
    "sequenceNo": 38938,
    "sizeBytes": 1400
  },
  {
    "timestamp": "2025-09-02T17:01:23.342+00:00",
    "sourceId": 12,
    "sequenceNo": 38939,
    "sizeBytes": 1400
  },
  {
    "timestamp": "2025-09-02T17:01:23.952+00:00",
    "sourceId": 12,
    "sequenceNo": 38940,
    "sizeBytes": 1400
  },
  {
    "timestamp": "2025-09-02T17:01:24.794+00:00",
    "sourceId": 12,
    "sequenceNo": 38941,
    "sizeBytes": 1400
  },
  {
    "timestamp": "2025-09-02T17:01:25.575+00:00",
    "sourceId": 12,
    "sequenceNo": 38942,
    "sizeBytes": 1400
  },
  {
    "timestamp": "2025-09-02T17:01:26.195+00:00",
    "sourceId": 12,
    "sequenceNo": 38943,
    "sizeBytes": 1400
  },
  {
    "timestamp": "2025-09-02T17:01:27.054+00:00",
    "sourceId": 12,
    "sequenceNo": 38944,
    "sizeBytes": 1400
  },
  {
    "timestamp": "2025-09-02T17:01:27.793+00:00",
    "sourceId": 12,
    "sequenceNo": 38945,
    "sizeBytes": 1400
  },
  {
    "timestamp": "2025-09-02T17:01:28.487+00:00",
    "sourceId": 12,
    "sequenceNo": 38946,
    "sizeBytes": 1400
  },
  {
    "timestamp": "2025-09-02T17:01:29.314+00:00",
    "sourceId": 12,
    "sequenceNo": 38947,
    "sizeBytes": 1400
  },
  {
    "timestamp": "2025-09-02T17:01:30.189+00:00",
    "sourceId": 12,
    "sequenceNo": 38948,
    "sizeBytes": 1400
  },
  {
    "timestamp": "2025-09-02T17:01:30.998+00:00",
    "sourceId": 12,
    "sequenceNo": 38949,
    "sizeBytes": 1400
  },
  {
    "timestamp": "2025-09-02T17:01:31.904+00:00",
    "sourceId": 12,
    "sequenceNo": 38950,
    "sizeBytes": 1400
  },
  {
    "timestamp": "2025-09-02T17:01:32.803+00:00",
    "sourceId": 12,
    "sequenceNo": 38951,
    "sizeBytes": 1400
  },
  {
    "timestamp": "2025-09-02T17:01:33.617+00:00",
    "sourceId": 12,
    "sequenceNo": 38952,
    "sizeBytes": 1400
  },
  {
    "timestamp": "2025-09-02T17:01:34.213+00:00",
    "sourceId": 12,
    "sequenceNo": 38953,
    "sizeBytes": 1400
  },
  {
    "timestamp": "2025-09-02T17:01:34.953+00:00",
    "sourceId": 12,
    "sequenceNo": 38954,
    "sizeBytes": 1400
  },
  {
    "timestamp": "2025-09-02T17:01:35.793+00:00",
    "sourceId": 12,
    "sequenceNo": 38955,
    "sizeBytes": 1400
  },
  {
    "timestamp": "2025-09-02T17:01:36.697+00:00",
    "sourceId": 12,
    "sequenceNo": 38956,
    "sizeBytes": 1400
  },
  {
    "timestamp": "2025-09-02T17:01:37.452+00:00",
    "sourceId": 12,
    "sequenceNo": 38957,
    "sizeBytes": 1400
  },
  {
    "timestamp": "2025-09-02T17:01:38.278+00:00",
    "sourceId": 12,
    "sequenceNo": 38958,
    "sizeBytes": 1400
  },
  {
    "timestamp": "2025-09-02T17:01:39.103+00:00",
    "sourceId": 12,
    "sequenceNo": 38959,
    "sizeBytes": 1400
  },
  {
    "timestamp": "2025-09-02T17:01:39.585+00:00",
    "sourceId": 12,
    "sequenceNo": 38960,
    "sizeBytes": 1400
  },
  {
    "timestamp": "2025-09-02T17:01:40.470+00:00",
    "sourceId": 12,
    "sequenceNo": 38961,
    "sizeBytes": 1400
  },
  {
    "timestamp": "2025-09-02T17:01:41.406+00:00",
    "sourceId": 12,
    "sequenceNo": 38962,
    "sizeBytes": 1400
  },
  {
    "timestamp": "2025-09-02T17:01:42.358+00:00",
    "sourceId": 12,
    "sequenceNo": 38963,
    "sizeBytes": 1400
  },
  {
    "timestamp": "2025-09-02T17:01:42.935+00:00",
    "sourceId": 12,
    "sequenceNo": 38964,
    "sizeBytes": 1400
  },
  {
    "timestamp": "2025-09-02T17:01:43.725+00:00",
    "sourceId": 12,
    "sequenceNo": 38965,
    "sizeBytes": 1400
  },
  {
    "timestamp": "2025-09-02T17:01:44.414+00:00",
    "sourceId": 12,
    "sequenceNo": 38966,
    "sizeBytes": 1400
  },
  {
    "timestamp": "2025-09-02T17:01:45.306+00:00",
    "sourceId": 12,
    "sequenceNo": 38967,
    "sizeBytes": 1400
  },
  {
    "timestamp": "2025-09-02T17:01:46.058+00:00",
    "sourceId": 12,
    "sequenceNo": 38968,
    "sizeBytes": 1400
  },
  {
    "timestamp": "2025-09-02T17:01:46.478+00:00",
    "sourceId": 12,
    "sequenceNo": 38969,
    "sizeBytes": 1400
  },
  {
    "timestamp": "2025-09-02T17:01:47.389+00:00",
    "sourceId": 12,
    "sequenceNo": 38970,
    "sizeBytes": 1400
  },
  {
    "timestamp": "2025-09-02T17:01:48.207+00:00",
    "sourceId": 12,
    "sequenceNo": 38971,
    "sizeBytes": 1400
  },
  {
    "timestamp": "2025-09-02T17:01:48.940+00:00",
    "sourceId": 12,
    "sequenceNo": 38972,
    "sizeBytes": 1400
  },
  {
    "timestamp": "2025-09-02T17:01:49.843+00:00",
    "sourceId": 12,
    "sequenceNo": 38973,
    "sizeBytes": 1400
  },
  {
    "timestamp": "2025-09-02T17:01:50.602+00:00",
    "sourceId": 12,
    "sequenceNo": 38974,
    "sizeBytes": 1400
  },
  {
    "timestamp": "2025-09-02T17:01:51.425+00:00",
    "sourceId": 12,
    "sequenceNo": 38975,
    "sizeBytes": 1400
  },
  {
    "timestamp": "2025-09-02T17:01:52.238+00:00",
    "sourceId": 12,
    "sequenceNo": 38976,
    "sizeBytes": 1400
  },
  {
    "timestamp": "2025-09-02T17:01:53.159+00:00",
    "sourceId": 12,
    "sequenceNo": 38977,
    "sizeBytes": 1400
  },
  {
    "timestamp": "2025-09-02T17:01:53.572+00:00",
    "sourceId": 12,
    "sequenceNo": 38978,
    "sizeBytes": 1400
  },
  {
    "timestamp": "2025-09-02T17:01:54.331+00:00",
    "sourceId": 12,
    "sequenceNo": 38979,
    "sizeBytes": 1400
  },
  {
    "timestamp": "2025-09-02T17:01:55.029+00:00",
    "sourceId": 12,
    "sequenceNo": 38980,
    "sizeBytes": 1400
  },
  {
    "timestamp": "2025-09-02T17:01:55.627+00:00",
    "sourceId": 12,
    "sequenceNo": 38981,
    "sizeBytes": 1400
  },
  {
    "timestamp": "2025-09-02T17:01:56.429+00:00",
    "sourceId": 12,
    "sequenceNo": 38982,
    "sizeBytes": 1400
  },
  {
    "timestamp": "2025-09-02T17:01:57.000+00:00",
    "sourceId": 12,
    "sequenceNo": 38983,
    "sizeBytes": 1400
  },
  {
    "timestamp": "2025-09-02T17:01:57.845+00:00",
    "sourceId": 12,
    "sequenceNo": 38984,
    "sizeBytes": 1400
  },
  {
    "timestamp": "2025-09-02T17:01:58.495+00:00",
    "sourceId": 12,
    "sequenceNo": 38985,
    "sizeBytes": 1400
  },
  {
    "timestamp": "2025-09-02T17:01:59.393+00:00",
    "sourceId": 12,
    "sequenceNo": 38986,
    "sizeBytes": 1400
  },
  {
    "timestamp": "2025-09-02T17:02:00.061+00:00",
    "sourceId": 12,
    "sequenceNo": 38987,
    "sizeBytes": 1400
  },
  {
    "timestamp": "2025-09-02T17:02:00.853+00:00",
    "sourceId": 12,
    "sequenceNo": 38988,
    "sizeBytes": 1400
  },
  {
    "timestamp": "2025-09-02T17:02:01.715+00:00",
    "sourceId": 12,
    "sequenceNo": 38989,
    "sizeBytes": 1400
  },
  {
    "timestamp": "2025-09-02T17:02:02.479+00:00",
    "sourceId": 12,
    "sequenceNo": 38990,
    "sizeBytes": 1400
  },
  {
    "timestamp": "2025-09-02T17:02:03.258+00:00",
    "sourceId": 12,
    "sequenceNo": 38991,
    "sizeBytes": 1400
  },
  {
    "timestamp": "2025-09-02T17:02:04.072+00:00",
    "sourceId": 12,
    "sequenceNo": 38992,
    "sizeBytes": 1400
  },
  {
    "timestamp": "2025-09-02T17:02:05.065+00:00",
    "sourceId": 12,
    "sequenceNo": 38993,
    "sizeBytes": 1400
  },
  {
    "timestamp": "2025-09-02T17:02:05.729+00:00",
    "sourceId": 12,
    "sequenceNo": 38994,
    "sizeBytes": 1400
  },
  {
    "timestamp": "2025-09-02T17:02:06.256+00:00",
    "sourceId": 12,
    "sequenceNo": 38995,
    "sizeBytes": 1400
  },
  {
    "timestamp": "2025-09-02T17:02:07.048+00:00",
    "sourceId": 12,
    "sequenceNo": 38996,
    "sizeBytes": 1400
  },
  {
    "timestamp": "2025-09-02T17:02:07.924+00:00",
    "sourceId": 12,
    "sequenceNo": 38997,
    "sizeBytes": 1400
  },
  {
    "timestamp": "2025-09-02T17:02:08.722+00:00",
    "sourceId": 12,
    "sequenceNo": 38998,
    "sizeBytes": 1400
  },
  {
    "timestamp": "2025-09-02T17:02:09.339+00:00",
    "sourceId": 12,
    "sequenceNo": 38999,
    "sizeBytes": 1400
  },
  {
    "timestamp": "2025-09-02T17:02:10.126+00:00",
    "sourceId": 12,
    "sequenceNo": 39000,
    "sizeBytes": 1400
  },
  {
    "timestamp": "2025-09-02T17:02:10.992+00:00",
    "sourceId": 12,
    "sequenceNo": 39001,
    "sizeBytes": 1400
  },
  {
    "timestamp": "2025-09-02T17:02:11.911+00:00",
    "sourceId": 12,
    "sequenceNo": 39002,
    "sizeBytes": 1400
  },
  {
    "timestamp": "2025-09-02T17:02:12.756+00:00",
    "sourceId": 12,
    "sequenceNo": 39003,
    "sizeBytes": 1400
  },
  {
    "timestamp": "2025-09-02T17:02:13.405+00:00",
    "sourceId": 12,
    "sequenceNo": 39004,
    "sizeBytes": 1400
  },
  {
    "timestamp": "2025-09-02T17:02:14.280+00:00",
    "sourceId": 12,
    "sequenceNo": 39005,
    "sizeBytes": 1400
  },
  {
    "timestamp": "2025-09-02T17:02:14.930+00:00",
    "sourceId": 12,
    "sequenceNo": 39006,
    "sizeBytes": 1400
  },
  {
    "timestamp": "2025-09-02T17:02:15.841+00:00",
    "sourceId": 12,
    "sequenceNo": 39007,
    "sizeBytes": 1400
  },
  {
    "timestamp": "2025-09-02T17:02:16.785+00:00",
    "sourceId": 12,
    "sequenceNo": 39008,
    "sizeBytes": 1400
  },
  {
    "timestamp": "2025-09-02T17:02:17.267+00:00",
    "sourceId": 12,
    "sequenceNo": 39009,
    "sizeBytes": 1400
  },
  {
    "timestamp": "2025-09-02T17:02:17.950+00:00",
    "sourceId": 12,
    "sequenceNo": 39010,
    "sizeBytes": 1400
  },
  {
    "timestamp": "2025-09-02T17:02:18.796+00:00",
    "sourceId": 12,
    "sequenceNo": 39011,
    "sizeBytes": 1400
  },
  {
    "timestamp": "2025-09-02T17:02:19.618+00:00",
    "sourceId": 12,
    "sequenceNo": 39012,
    "sizeBytes": 1400
  },
  {
    "timestamp": "2025-09-02T17:02:20.237+00:00",
    "sourceId": 12,
    "sequenceNo": 39013,
    "sizeBytes": 1400
  },
  {
    "timestamp": "2025-09-02T17:02:21.124+00:00",
    "sourceId": 12,
    "sequenceNo": 39014,
    "sizeBytes": 1400
  },
  {
    "timestamp": "2025-09-02T17:02:21.671+00:00",
    "sourceId": 12,
    "sequenceNo": 39015,
    "sizeBytes": 1400
  },
  {
    "timestamp": "2025-09-02T17:02:22.283+00:00",
    "sourceId": 12,
    "sequenceNo": 39016,
    "sizeBytes": 1400
  },
  {
    "timestamp": "2025-09-02T17:02:23.136+00:00",
    "sourceId": 12,
    "sequenceNo": 39017,
    "sizeBytes": 1400
  },
  {
    "timestamp": "2025-09-02T17:02:23.805+00:00",
    "sourceId": 12,
    "sequenceNo": 39018,
    "sizeBytes": 1400
  },
  {
    "timestamp": "2025-09-02T17:02:24.488+00:00",
    "sourceId": 12,
    "sequenceNo": 39019,
    "sizeBytes": 1400
  },
  {
    "timestamp": "2025-09-02T17:02:25.169+00:00",
    "sourceId": 12,
    "sequenceNo": 39020,
    "sizeBytes": 1400
  },
  {
    "timestamp": "2025-09-02T17:02:26.054+00:00",
    "sourceId": 12,
    "sequenceNo": 39021,
    "sizeBytes": 1400
  },
  {
    "timestamp": "2025-09-02T17:02:27.029+00:00",
    "sourceId": 12,
    "sequenceNo": 39022,
    "sizeBytes": 1400
  },
  {
    "timestamp": "2025-09-02T17:02:27.862+00:00",
    "sourceId": 12,
    "sequenceNo": 39023,
    "sizeBytes": 1400
  },
  {
    "timestamp": "2025-09-02T17:02:28.908+00:00",
    "sourceId": 12,
    "sequenceNo": 39024,
    "sizeBytes": 1400
  },
  {
    "timestamp": "2025-09-02T17:02:29.779+00:00",
    "sourceId": 12,
    "sequenceNo": 39025,
    "sizeBytes": 1400
  },
  {
    "timestamp": "2025-09-02T17:02:30.401+00:00",
    "sourceId": 12,
    "sequenceNo": 39026,
    "sizeBytes": 1400
  },
  {
    "timestamp": "2025-09-02T17:02:30.751+00:00",
    "sourceId": 12,
    "sequenceNo": 39027,
    "sizeBytes": 1400
  },
  {
    "timestamp": "2025-09-02T17:02:31.719+00:00",
    "sourceId": 12,
    "sequenceNo": 39028,
    "sizeBytes": 1400
  },
  {
    "timestamp": "2025-09-02T17:02:32.514+00:00",
    "sourceId": 12,
    "sequenceNo": 39029,
    "sizeBytes": 1400
  },
  {
    "timestamp": "2025-09-02T17:02:33.354+00:00",
    "sourceId": 12,
    "sequenceNo": 39030,
    "sizeBytes": 1400
  },
  {
    "timestamp": "2025-09-02T17:02:34.209+00:00",
    "sourceId": 12,
    "sequenceNo": 39031,
    "sizeBytes": 1400
  },
  {
    "timestamp": "2025-09-02T17:02:35.070+00:00",
    "sourceId": 12,
    "sequenceNo": 39032,
    "sizeBytes": 1400
  },
  {
    "timestamp": "2025-09-02T17:02:35.962+00:00",
    "sourceId": 12,
    "sequenceNo": 39033,
    "sizeBytes": 1400
  },
  {
    "timestamp": "2025-09-02T17:02:36.691+00:00",
    "sourceId": 12,
    "sequenceNo": 39034,
    "sizeBytes": 1400
  },
  {
    "timestamp": "2025-09-02T17:02:37.442+00:00",
    "sourceId": 12,
    "sequenceNo": 39035,
    "sizeBytes": 1400
  },
  {
    "timestamp": "2025-09-02T17:02:37.894+00:00",
    "sourceId": 12,
    "sequenceNo": 39036,
    "sizeBytes": 1400
  },
  {
    "timestamp": "2025-09-02T17:02:38.672+00:00",
    "sourceId": 12,
    "sequenceNo": 39037,
    "sizeBytes": 1400
  },
  {
    "timestamp": "2025-09-02T17:02:39.149+00:00",
    "sourceId": 12,
    "sequenceNo": 39038,
    "sizeBytes": 1400
  },
  {
    "timestamp": "2025-09-02T17:02:39.907+00:00",
    "sourceId": 12,
    "sequenceNo": 39039,
    "sizeBytes": 1400
  },
  {
    "timestamp": "2025-09-02T17:02:40.785+00:00",
    "sourceId": 12,
    "sequenceNo": 39040,
    "sizeBytes": 1400
  },
  {
    "timestamp": "2025-09-02T17:02:41.647+00:00",
    "sourceId": 12,
    "sequenceNo": 39041,
    "sizeBytes": 1400
  },
  {
    "timestamp": "2025-09-02T17:02:42.387+00:00",
    "sourceId": 12,
    "sequenceNo": 39042,
    "sizeBytes": 1400
  },
  {
    "timestamp": "2025-09-02T17:02:43.176+00:00",
    "sourceId": 12,
    "sequenceNo": 39043,
    "sizeBytes": 1400
  },
  {
    "timestamp": "2025-09-02T17:02:44.077+00:00",
    "sourceId": 12,
    "sequenceNo": 39044,
    "sizeBytes": 1400
  },
  {
    "timestamp": "2025-09-02T17:02:45.043+00:00",
    "sourceId": 12,
    "sequenceNo": 39045,
    "sizeBytes": 1400
  },
  {
    "timestamp": "2025-09-02T17:02:45.742+00:00",
    "sourceId": 12,
    "sequenceNo": 39046,
    "sizeBytes": 1400
  },
  {
    "timestamp": "2025-09-02T17:02:46.601+00:00",
    "sourceId": 12,
    "sequenceNo": 39047,
    "sizeBytes": 1400
  },
  {
    "timestamp": "2025-09-02T17:02:47.260+00:00",
    "sourceId": 12,
    "sequenceNo": 39048,
    "sizeBytes": 1400
  },
  {
    "timestamp": "2025-09-02T17:02:48.105+00:00",
    "sourceId": 12,
    "sequenceNo": 39049,
    "sizeBytes": 1400
  },
  {
    "timestamp": "2025-09-02T17:02:48.673+00:00",
    "sourceId": 12,
    "sequenceNo": 39050,
    "sizeBytes": 1400
  },
  {
    "timestamp": "2025-09-02T17:02:49.560+00:00",
    "sourceId": 12,
    "sequenceNo": 39051,
    "sizeBytes": 1400
  },
  {
    "timestamp": "2025-09-02T17:02:50.167+00:00",
    "sourceId": 12,
    "sequenceNo": 39052,
    "sizeBytes": 1400
  },
  {
    "timestamp": "2025-09-02T17:02:50.840+00:00",
    "sourceId": 12,
    "sequenceNo": 39053,
    "sizeBytes": 1400
  },
  {
    "timestamp": "2025-09-02T17:02:51.452+00:00",
    "sourceId": 12,
    "sequenceNo": 39054,
    "sizeBytes": 1400
  },
  {
    "timestamp": "2025-09-02T17:02:52.180+00:00",
    "sourceId": 12,
    "sequenceNo": 39055,
    "sizeBytes": 1400
  },
  {
    "timestamp": "2025-09-02T17:02:52.989+00:00",
    "sourceId": 12,
    "sequenceNo": 39056,
    "sizeBytes": 1400
  },
  {
    "timestamp": "2025-09-02T17:02:53.645+00:00",
    "sourceId": 12,
    "sequenceNo": 39057,
    "sizeBytes": 1400
  },
  {
    "timestamp": "2025-09-02T17:02:54.513+00:00",
    "sourceId": 12,
    "sequenceNo": 39058,
    "sizeBytes": 1400
  },
  {
    "timestamp": "2025-09-02T17:02:55.107+00:00",
    "sourceId": 12,
    "sequenceNo": 39059,
    "sizeBytes": 1400
  },
  {
    "timestamp": "2025-09-02T17:02:56.095+00:00",
    "sourceId": 12,
    "sequenceNo": 39060,
    "sizeBytes": 1400
  },
  {
    "timestamp": "2025-09-02T17:02:57.045+00:00",
    "sourceId": 12,
    "sequenceNo": 39061,
    "sizeBytes": 1400
  },
  {
    "timestamp": "2025-09-02T17:02:57.849+00:00",
    "sourceId": 12,
    "sequenceNo": 39062,
    "sizeBytes": 1400
  },
  {
    "timestamp": "2025-09-02T17:02:58.586+00:00",
    "sourceId": 12,
    "sequenceNo": 39063,
    "sizeBytes": 1400
  },
  {
    "timestamp": "2025-09-02T17:02:59.099+00:00",
    "sourceId": 12,
    "sequenceNo": 39064,
    "sizeBytes": 1400
  },
  {
    "timestamp": "2025-09-02T17:02:59.985+00:00",
    "sourceId": 12,
    "sequenceNo": 39065,
    "sizeBytes": 1400
  },
  {
    "timestamp": "2025-09-02T17:03:00.922+00:00",
    "sourceId": 12,
    "sequenceNo": 39066,
    "sizeBytes": 1400
  },
  {
    "timestamp": "2025-09-02T17:03:01.744+00:00",
    "sourceId": 12,
    "sequenceNo": 39067,
    "sizeBytes": 1400
  },
  {
    "timestamp": "2025-09-02T17:03:02.633+00:00",
    "sourceId": 12,
    "sequenceNo": 39068,
    "sizeBytes": 1400
  },
  {
    "timestamp": "2025-09-02T17:03:03.564+00:00",
    "sourceId": 12,
    "sequenceNo": 39069,
    "sizeBytes": 1400
  },
  {
    "timestamp": "2025-09-02T17:03:04.208+00:00",
    "sourceId": 12,
    "sequenceNo": 39070,
    "sizeBytes": 1400
  },
  {
    "timestamp": "2025-09-02T17:03:04.679+00:00",
    "sourceId": 12,
    "sequenceNo": 39071,
    "sizeBytes": 1400
  },
  {
    "timestamp": "2025-09-02T17:03:05.524+00:00",
    "sourceId": 12,
    "sequenceNo": 39072,
    "sizeBytes": 1400
  },
  {
    "timestamp": "2025-09-02T17:03:06.287+00:00",
    "sourceId": 12,
    "sequenceNo": 39073,
    "sizeBytes": 1400
  },
  {
    "timestamp": "2025-09-02T17:03:06.817+00:00",
    "sourceId": 12,
    "sequenceNo": 39074,
    "sizeBytes": 1400
  },
  {
    "timestamp": "2025-09-02T17:03:07.663+00:00",
    "sourceId": 12,
    "sequenceNo": 39075,
    "sizeBytes": 1400
  },
  {
    "timestamp": "2025-09-02T17:03:08.383+00:00",
    "sourceId": 12,
    "sequenceNo": 39076,
    "sizeBytes": 1400
  },
  {
    "timestamp": "2025-09-02T17:03:09.249+00:00",
    "sourceId": 12,
    "sequenceNo": 39077,
    "sizeBytes": 1400
  },
  {
    "timestamp": "2025-09-02T17:03:10.105+00:00",
    "sourceId": 12,
    "sequenceNo": 39078,
    "sizeBytes": 1400
  },
  {
    "timestamp": "2025-09-02T17:03:10.912+00:00",
    "sourceId": 12,
    "sequenceNo": 39079,
    "sizeBytes": 1400
  },
  {
    "timestamp": "2025-09-02T17:03:11.815+00:00",
    "sourceId": 12,
    "sequenceNo": 39080,
    "sizeBytes": 1400
  },
  {
    "timestamp": "2025-09-02T17:03:12.700+00:00",
    "sourceId": 12,
    "sequenceNo": 39081,
    "sizeBytes": 1400
  },
  {
    "timestamp": "2025-09-02T17:03:13.549+00:00",
    "sourceId": 12,
    "sequenceNo": 39082,
    "sizeBytes": 1400
  },
  {
    "timestamp": "2025-09-02T17:03:14.223+00:00",
    "sourceId": 12,
    "sequenceNo": 39083,
    "sizeBytes": 1400
  },
  {
    "timestamp": "2025-09-02T17:03:14.820+00:00",
    "sourceId": 12,
    "sequenceNo": 39084,
    "sizeBytes": 1400
  },
  {
    "timestamp": "2025-09-02T17:03:15.674+00:00",
    "sourceId": 12,
    "sequenceNo": 39085,
    "sizeBytes": 1400
  },
  {
    "timestamp": "2025-09-02T17:03:16.493+00:00",
    "sourceId": 12,
    "sequenceNo": 39086,
    "sizeBytes": 1400
  },
  {
    "timestamp": "2025-09-02T17:03:17.305+00:00",
    "sourceId": 12,
    "sequenceNo": 39087,
    "sizeBytes": 1400
  },
  {
    "timestamp": "2025-09-02T17:03:17.924+00:00",
    "sourceId": 12,
    "sequenceNo": 39088,
    "sizeBytes": 1400
  },
  {
    "timestamp": "2025-09-02T17:03:18.740+00:00",
    "sourceId": 12,
    "sequenceNo": 39089,
    "sizeBytes": 1400
  },
  {
    "timestamp": "2025-09-02T17:03:19.530+00:00",
    "sourceId": 12,
    "sequenceNo": 39090,
    "sizeBytes": 1400
  },
  {
    "timestamp": "2025-09-02T17:03:20.097+00:00",
    "sourceId": 12,
    "sequenceNo": 39091,
    "sizeBytes": 1400
  },
  {
    "timestamp": "2025-09-02T17:03:20.697+00:00",
    "sourceId": 12,
    "sequenceNo": 39092,
    "sizeBytes": 1400
  },
  {
    "timestamp": "2025-09-02T17:03:21.382+00:00",
    "sourceId": 12,
    "sequenceNo": 39093,
    "sizeBytes": 1400
  },
  {
    "timestamp": "2025-09-02T17:03:22.293+00:00",
    "sourceId": 12,
    "sequenceNo": 39094,
    "sizeBytes": 1400
  },
  {
    "timestamp": "2025-09-02T17:03:23.085+00:00",
    "sourceId": 12,
    "sequenceNo": 39095,
    "sizeBytes": 1400
  },
  {
    "timestamp": "2025-09-02T17:03:23.990+00:00",
    "sourceId": 12,
    "sequenceNo": 39096,
    "sizeBytes": 1400
  },
  {
    "timestamp": "2025-09-02T17:03:24.679+00:00",
    "sourceId": 12,
    "sequenceNo": 39097,
    "sizeBytes": 1400
  },
  {
    "timestamp": "2025-09-02T17:03:25.453+00:00",
    "sourceId": 12,
    "sequenceNo": 39098,
    "sizeBytes": 1400
  },
  {
    "timestamp": "2025-09-02T17:03:26.187+00:00",
    "sourceId": 12,
    "sequenceNo": 39099,
    "sizeBytes": 1400
  },
  {
    "timestamp": "2025-09-02T17:03:27.061+00:00",
    "sourceId": 12,
    "sequenceNo": 39100,
    "sizeBytes": 1400
  },
  {
    "timestamp": "2025-09-02T17:03:27.797+00:00",
    "sourceId": 12,
    "sequenceNo": 39101,
    "sizeBytes": 1400
  },
  {
    "timestamp": "2025-09-02T17:03:28.537+00:00",
    "sourceId": 12,
    "sequenceNo": 39102,
    "sizeBytes": 1400
  },
  {
    "timestamp": "2025-09-02T17:03:29.271+00:00",
    "sourceId": 12,
    "sequenceNo": 39103,
    "sizeBytes": 1400
  },
  {
    "timestamp": "2025-09-02T17:03:29.600+00:00",
    "sourceId": 12,
    "sequenceNo": 39104,
    "sizeBytes": 1400
  },
  {
    "timestamp": "2025-09-02T17:03:30.288+00:00",
    "sourceId": 12,
    "sequenceNo": 39105,
    "sizeBytes": 1400
  },
  {
    "timestamp": "2025-09-02T17:03:31.198+00:00",
    "sourceId": 12,
    "sequenceNo": 39106,
    "sizeBytes": 1400
  },
  {
    "timestamp": "2025-09-02T17:03:32.071+00:00",
    "sourceId": 12,
    "sequenceNo": 39107,
    "sizeBytes": 1400
  },
  {
    "timestamp": "2025-09-02T17:03:32.938+00:00",
    "sourceId": 12,
    "sequenceNo": 39108,
    "sizeBytes": 1400
  },
  {
    "timestamp": "2025-09-02T17:03:33.645+00:00",
    "sourceId": 12,
    "sequenceNo": 39109,
    "sizeBytes": 1400
  },
  {
    "timestamp": "2025-09-02T17:03:34.429+00:00",
    "sourceId": 12,
    "sequenceNo": 39110,
    "sizeBytes": 1400
  },
  {
    "timestamp": "2025-09-02T17:03:34.988+00:00",
    "sourceId": 12,
    "sequenceNo": 39111,
    "sizeBytes": 1400
  },
  {
    "timestamp": "2025-09-02T17:03:35.776+00:00",
    "sourceId": 12,
    "sequenceNo": 39112,
    "sizeBytes": 1400
  },
  {
    "timestamp": "2025-09-02T17:03:36.343+00:00",
    "sourceId": 12,
    "sequenceNo": 39113,
    "sizeBytes": 1400
  },
  {
    "timestamp": "2025-09-02T17:03:37.201+00:00",
    "sourceId": 12,
    "sequenceNo": 39114,
    "sizeBytes": 1400
  },
  {
    "timestamp": "2025-09-02T17:03:37.793+00:00",
    "sourceId": 12,
    "sequenceNo": 39115,
    "sizeBytes": 1400
  },
  {
    "timestamp": "2025-09-02T17:03:38.612+00:00",
    "sourceId": 12,
    "sequenceNo": 39116,
    "sizeBytes": 1400
  },
  {
    "timestamp": "2025-09-02T17:03:39.340+00:00",
    "sourceId": 12,
    "sequenceNo": 39117,
    "sizeBytes": 1400
  },
  {
    "timestamp": "2025-09-02T17:03:40.049+00:00",
    "sourceId": 12,
    "sequenceNo": 39118,
    "sizeBytes": 1400
  },
  {
    "timestamp": "2025-09-02T17:03:40.945+00:00",
    "sourceId": 12,
    "sequenceNo": 39119,
    "sizeBytes": 1400
  },
  {
    "timestamp": "2025-09-02T17:03:41.431+00:00",
    "sourceId": 12,
    "sequenceNo": 39120,
    "sizeBytes": 1400
  },
  {
    "timestamp": "2025-09-02T17:03:41.991+00:00",
    "sourceId": 12,
    "sequenceNo": 39121,
    "sizeBytes": 1400
  },
  {
    "timestamp": "2025-09-02T17:03:42.646+00:00",
    "sourceId": 12,
    "sequenceNo": 39122,
    "sizeBytes": 1400
  },
  {
    "timestamp": "2025-09-02T17:03:43.538+00:00",
    "sourceId": 12,
    "sequenceNo": 39123,
    "sizeBytes": 1400
  },
  {
    "timestamp": "2025-09-02T17:03:44.226+00:00",
    "sourceId": 12,
    "sequenceNo": 39124,
    "sizeBytes": 1400
  },
  {
    "timestamp": "2025-09-02T17:03:44.767+00:00",
    "sourceId": 12,
    "sequenceNo": 39125,
    "sizeBytes": 1400
  },
  {
    "timestamp": "2025-09-02T17:03:45.605+00:00",
    "sourceId": 12,
    "sequenceNo": 39126,
    "sizeBytes": 1400
  },
  {
    "timestamp": "2025-09-02T17:03:46.515+00:00",
    "sourceId": 12,
    "sequenceNo": 39127,
    "sizeBytes": 1400
  },
  {
    "timestamp": "2025-09-02T17:03:47.215+00:00",
    "sourceId": 12,
    "sequenceNo": 39128,
    "sizeBytes": 1400
  },
  {
    "timestamp": "2025-09-02T17:03:48.072+00:00",
    "sourceId": 12,
    "sequenceNo": 39129,
    "sizeBytes": 1400
  },
  {
    "timestamp": "2025-09-02T17:03:48.871+00:00",
    "sourceId": 12,
    "sequenceNo": 39130,
    "sizeBytes": 1400
  },
  {
    "timestamp": "2025-09-02T17:03:49.709+00:00",
    "sourceId": 12,
    "sequenceNo": 39131,
    "sizeBytes": 1400
  },
  {
    "timestamp": "2025-09-02T17:03:50.610+00:00",
    "sourceId": 12,
    "sequenceNo": 39132,
    "sizeBytes": 1400
  },
  {
    "timestamp": "2025-09-02T17:03:51.506+00:00",
    "sourceId": 12,
    "sequenceNo": 39133,
    "sizeBytes": 1400
  },
  {
    "timestamp": "2025-09-02T17:03:52.135+00:00",
    "sourceId": 12,
    "sequenceNo": 39134,
    "sizeBytes": 1400
  },
  {
    "timestamp": "2025-09-02T17:03:52.783+00:00",
    "sourceId": 12,
    "sequenceNo": 39135,
    "sizeBytes": 1400
  },
  {
    "timestamp": "2025-09-02T17:03:53.513+00:00",
    "sourceId": 12,
    "sequenceNo": 39136,
    "sizeBytes": 1400
  },
  {
    "timestamp": "2025-09-02T17:03:54.244+00:00",
    "sourceId": 12,
    "sequenceNo": 39137,
    "sizeBytes": 1400
  },
  {
    "timestamp": "2025-09-02T17:03:54.826+00:00",
    "sourceId": 12,
    "sequenceNo": 39138,
    "sizeBytes": 1400
  },
  {
    "timestamp": "2025-09-02T17:03:55.475+00:00",
    "sourceId": 12,
    "sequenceNo": 39139,
    "sizeBytes": 1400
  },
  {
    "timestamp": "2025-09-02T17:03:56.187+00:00",
    "sourceId": 12,
    "sequenceNo": 39140,
    "sizeBytes": 1400
  },
  {
    "timestamp": "2025-09-02T17:03:57.008+00:00",
    "sourceId": 12,
    "sequenceNo": 39141,
    "sizeBytes": 1400
  },
  {
    "timestamp": "2025-09-02T17:03:57.765+00:00",
    "sourceId": 12,
    "sequenceNo": 39142,
    "sizeBytes": 1400
  },
  {
    "timestamp": "2025-09-02T17:03:58.668+00:00",
    "sourceId": 12,
    "sequenceNo": 39143,
    "sizeBytes": 1400
  },
  {
    "timestamp": "2025-09-02T17:03:59.462+00:00",
    "sourceId": 12,
    "sequenceNo": 39144,
    "sizeBytes": 1400
  },
  {
    "timestamp": "2025-09-02T17:04:00.244+00:00",
    "sourceId": 12,
    "sequenceNo": 39145,
    "sizeBytes": 1400
  },
  {
    "timestamp": "2025-09-02T17:04:00.607+00:00",
    "sourceId": 12,
    "sequenceNo": 39146,
    "sizeBytes": 1400
  },
  {
    "timestamp": "2025-09-02T17:04:01.494+00:00",
    "sourceId": 12,
    "sequenceNo": 39147,
    "sizeBytes": 1400
  },
  {
    "timestamp": "2025-09-02T17:04:02.178+00:00",
    "sourceId": 12,
    "sequenceNo": 39148,
    "sizeBytes": 1400
  },
  {
    "timestamp": "2025-09-02T17:04:03.060+00:00",
    "sourceId": 12,
    "sequenceNo": 39149,
    "sizeBytes": 1400
  },
  {
    "timestamp": "2025-09-02T17:04:03.595+00:00",
    "sourceId": 12,
    "sequenceNo": 39150,
    "sizeBytes": 1400
  },
  {
    "timestamp": "2025-09-02T17:04:04.552+00:00",
    "sourceId": 12,
    "sequenceNo": 39151,
    "sizeBytes": 1400
  },
  {
    "timestamp": "2025-09-02T17:04:05.411+00:00",
    "sourceId": 12,
    "sequenceNo": 39152,
    "sizeBytes": 1400
  },
  {
    "timestamp": "2025-09-02T17:04:06.052+00:00",
    "sourceId": 12,
    "sequenceNo": 39153,
    "sizeBytes": 1400
  },
  {
    "timestamp": "2025-09-02T17:04:06.923+00:00",
    "sourceId": 12,
    "sequenceNo": 39154,
    "sizeBytes": 1400
  },
  {
    "timestamp": "2025-09-02T17:04:07.814+00:00",
    "sourceId": 12,
    "sequenceNo": 39155,
    "sizeBytes": 1400
  },
  {
    "timestamp": "2025-09-02T17:04:08.827+00:00",
    "sourceId": 12,
    "sequenceNo": 39156,
    "sizeBytes": 1400
  },
  {
    "timestamp": "2025-09-02T17:04:09.440+00:00",
    "sourceId": 12,
    "sequenceNo": 39157,
    "sizeBytes": 1400
  },
  {
    "timestamp": "2025-09-02T17:04:10.301+00:00",
    "sourceId": 12,
    "sequenceNo": 39158,
    "sizeBytes": 1400
  },
  {
    "timestamp": "2025-09-02T17:04:11.201+00:00",
    "sourceId": 12,
    "sequenceNo": 39159,
    "sizeBytes": 1400
  },
  {
    "timestamp": "2025-09-02T17:04:12.106+00:00",
    "sourceId": 12,
    "sequenceNo": 39160,
    "sizeBytes": 1400
  },
  {
    "timestamp": "2025-09-02T17:04:13.064+00:00",
    "sourceId": 12,
    "sequenceNo": 39161,
    "sizeBytes": 1400
  },
  {
    "timestamp": "2025-09-02T17:04:13.912+00:00",
    "sourceId": 12,
    "sequenceNo": 39162,
    "sizeBytes": 1400
  },
  {
    "timestamp": "2025-09-02T17:04:14.817+00:00",
    "sourceId": 12,
    "sequenceNo": 39163,
    "sizeBytes": 1400
  },
  {
    "timestamp": "2025-09-02T17:04:15.628+00:00",
    "sourceId": 12,
    "sequenceNo": 39164,
    "sizeBytes": 1400
  },
  {
    "timestamp": "2025-09-02T17:04:16.331+00:00",
    "sourceId": 12,
    "sequenceNo": 39165,
    "sizeBytes": 1400
  },
  {
    "timestamp": "2025-09-02T17:04:17.243+00:00",
    "sourceId": 12,
    "sequenceNo": 39166,
    "sizeBytes": 1400
  },
  {
    "timestamp": "2025-09-02T17:04:18.100+00:00",
    "sourceId": 12,
    "sequenceNo": 39167,
    "sizeBytes": 1400
  },
  {
    "timestamp": "2025-09-02T17:04:18.959+00:00",
    "sourceId": 12,
    "sequenceNo": 39168,
    "sizeBytes": 1400
  },
  {
    "timestamp": "2025-09-02T17:04:19.819+00:00",
    "sourceId": 12,
    "sequenceNo": 39169,
    "sizeBytes": 1400
  },
  {
    "timestamp": "2025-09-02T17:04:20.736+00:00",
    "sourceId": 12,
    "sequenceNo": 39170,
    "sizeBytes": 1400
  },
  {
    "timestamp": "2025-09-02T17:04:21.670+00:00",
    "sourceId": 12,
    "sequenceNo": 39171,
    "sizeBytes": 1400
  },
  {
    "timestamp": "2025-09-02T17:04:22.528+00:00",
    "sourceId": 12,
    "sequenceNo": 39172,
    "sizeBytes": 1400
  },
  {
    "timestamp": "2025-09-02T17:04:23.394+00:00",
    "sourceId": 12,
    "sequenceNo": 39173,
    "sizeBytes": 1400
  },
  {
    "timestamp": "2025-09-02T17:04:24.349+00:00",
    "sourceId": 12,
    "sequenceNo": 39174,
    "sizeBytes": 1400
  },
  {
    "timestamp": "2025-09-02T17:04:25.089+00:00",
    "sourceId": 12,
    "sequenceNo": 39175,
    "sizeBytes": 1400
  },
  {
    "timestamp": "2025-09-02T17:04:25.687+00:00",
    "sourceId": 12,
    "sequenceNo": 39176,
    "sizeBytes": 1400
  },
  {
    "timestamp": "2025-09-02T17:04:26.674+00:00",
    "sourceId": 12,
    "sequenceNo": 39177,
    "sizeBytes": 1400
  },
  {
    "timestamp": "2025-09-02T17:04:27.424+00:00",
    "sourceId": 12,
    "sequenceNo": 39178,
    "sizeBytes": 1400
  },
  {
    "timestamp": "2025-09-02T17:04:28.058+00:00",
    "sourceId": 12,
    "sequenceNo": 39179,
    "sizeBytes": 1400
  },
  {
    "timestamp": "2025-09-02T17:04:28.880+00:00",
    "sourceId": 12,
    "sequenceNo": 39180,
    "sizeBytes": 1400
  },
  {
    "timestamp": "2025-09-02T17:04:29.723+00:00",
    "sourceId": 12,
    "sequenceNo": 39181,
    "sizeBytes": 1400
  },
  {
    "timestamp": "2025-09-02T17:04:30.323+00:00",
    "sourceId": 12,
    "sequenceNo": 39182,
    "sizeBytes": 1400
  },
  {
    "timestamp": "2025-09-02T17:04:30.888+00:00",
    "sourceId": 12,
    "sequenceNo": 39183,
    "sizeBytes": 1400
  },
  {
    "timestamp": "2025-09-02T17:04:31.783+00:00",
    "sourceId": 12,
    "sequenceNo": 39184,
    "sizeBytes": 1400
  },
  {
    "timestamp": "2025-09-02T17:04:32.455+00:00",
    "sourceId": 12,
    "sequenceNo": 39185,
    "sizeBytes": 1400
  },
  {
    "timestamp": "2025-09-02T17:04:33.155+00:00",
    "sourceId": 12,
    "sequenceNo": 39186,
    "sizeBytes": 1400
  },
  {
    "timestamp": "2025-09-02T17:04:33.674+00:00",
    "sourceId": 12,
    "sequenceNo": 39187,
    "sizeBytes": 1400
  },
  {
    "timestamp": "2025-09-02T17:04:34.454+00:00",
    "sourceId": 12,
    "sequenceNo": 39188,
    "sizeBytes": 1400
  },
  {
    "timestamp": "2025-09-02T17:04:35.435+00:00",
    "sourceId": 12,
    "sequenceNo": 39189,
    "sizeBytes": 1400
  },
  {
    "timestamp": "2025-09-02T17:04:36.201+00:00",
    "sourceId": 12,
    "sequenceNo": 39190,
    "sizeBytes": 1400
  },
  {
    "timestamp": "2025-09-02T17:04:36.671+00:00",
    "sourceId": 12,
    "sequenceNo": 39191,
    "sizeBytes": 1400
  },
  {
    "timestamp": "2025-09-02T17:04:37.408+00:00",
    "sourceId": 12,
    "sequenceNo": 39192,
    "sizeBytes": 1400
  },
  {
    "timestamp": "2025-09-02T17:04:38.276+00:00",
    "sourceId": 12,
    "sequenceNo": 39193,
    "sizeBytes": 1400
  },
  {
    "timestamp": "2025-09-02T17:04:38.967+00:00",
    "sourceId": 12,
    "sequenceNo": 39194,
    "sizeBytes": 1400
  },
  {
    "timestamp": "2025-09-02T17:04:39.771+00:00",
    "sourceId": 12,
    "sequenceNo": 39195,
    "sizeBytes": 1400
  },
  {
    "timestamp": "2025-09-02T17:04:40.625+00:00",
    "sourceId": 12,
    "sequenceNo": 39196,
    "sizeBytes": 1400
  },
  {
    "timestamp": "2025-09-02T17:04:41.344+00:00",
    "sourceId": 12,
    "sequenceNo": 39197,
    "sizeBytes": 1400
  },
  {
    "timestamp": "2025-09-02T17:04:42.064+00:00",
    "sourceId": 12,
    "sequenceNo": 39198,
    "sizeBytes": 1400
  },
  {
    "timestamp": "2025-09-02T17:04:42.826+00:00",
    "sourceId": 12,
    "sequenceNo": 39199,
    "sizeBytes": 1400
  },
  {
    "timestamp": "2025-09-02T17:04:43.681+00:00",
    "sourceId": 12,
    "sequenceNo": 39200,
    "sizeBytes": 1400
  },
  {
    "timestamp": "2025-09-02T17:04:44.336+00:00",
    "sourceId": 12,
    "sequenceNo": 39201,
    "sizeBytes": 1400
  },
  {
    "timestamp": "2025-09-02T17:04:45.260+00:00",
    "sourceId": 12,
    "sequenceNo": 39202,
    "sizeBytes": 1400
  },
  {
    "timestamp": "2025-09-02T17:04:46.036+00:00",
    "sourceId": 12,
    "sequenceNo": 39203,
    "sizeBytes": 1400
  },
  {
    "timestamp": "2025-09-02T17:04:46.792+00:00",
    "sourceId": 12,
    "sequenceNo": 39204,
    "sizeBytes": 1400
  },
  {
    "timestamp": "2025-09-02T17:04:47.418+00:00",
    "sourceId": 12,
    "sequenceNo": 39205,
    "sizeBytes": 1400
  },
  {
    "timestamp": "2025-09-02T17:04:48.270+00:00",
    "sourceId": 12,
    "sequenceNo": 39206,
    "sizeBytes": 1400
  },
  {
    "timestamp": "2025-09-02T17:04:49.183+00:00",
    "sourceId": 12,
    "sequenceNo": 39207,
    "sizeBytes": 1400
  },
  {
    "timestamp": "2025-09-02T17:04:49.942+00:00",
    "sourceId": 12,
    "sequenceNo": 39208,
    "sizeBytes": 1400
  },
  {
    "timestamp": "2025-09-02T17:04:50.722+00:00",
    "sourceId": 12,
    "sequenceNo": 39209,
    "sizeBytes": 1400
  },
  {
    "timestamp": "2025-09-02T17:04:51.557+00:00",
    "sourceId": 12,
    "sequenceNo": 39210,
    "sizeBytes": 1400
  },
  {
    "timestamp": "2025-09-02T17:04:52.361+00:00",
    "sourceId": 12,
    "sequenceNo": 39211,
    "sizeBytes": 1400
  },
  {
    "timestamp": "2025-09-02T17:04:52.888+00:00",
    "sourceId": 12,
    "sequenceNo": 39212,
    "sizeBytes": 1400
  },
  {
    "timestamp": "2025-09-02T17:04:53.675+00:00",
    "sourceId": 12,
    "sequenceNo": 39213,
    "sizeBytes": 1400
  },
  {
    "timestamp": "2025-09-02T17:04:54.322+00:00",
    "sourceId": 12,
    "sequenceNo": 39214,
    "sizeBytes": 1400
  },
  {
    "timestamp": "2025-09-02T17:04:55.139+00:00",
    "sourceId": 12,
    "sequenceNo": 39215,
    "sizeBytes": 1400
  },
  {
    "timestamp": "2025-09-02T17:04:55.623+00:00",
    "sourceId": 12,
    "sequenceNo": 39216,
    "sizeBytes": 1400
  },
  {
    "timestamp": "2025-09-02T17:04:56.411+00:00",
    "sourceId": 12,
    "sequenceNo": 39217,
    "sizeBytes": 1400
  },
  {
    "timestamp": "2025-09-02T17:04:57.284+00:00",
    "sourceId": 12,
    "sequenceNo": 39218,
    "sizeBytes": 1400
  },
  {
    "timestamp": "2025-09-02T17:04:58.135+00:00",
    "sourceId": 12,
    "sequenceNo": 39219,
    "sizeBytes": 1400
  },
  {
    "timestamp": "2025-09-02T17:04:58.612+00:00",
    "sourceId": 12,
    "sequenceNo": 39220,
    "sizeBytes": 1400
  },
  {
    "timestamp": "2025-09-02T17:04:59.473+00:00",
    "sourceId": 12,
    "sequenceNo": 39221,
    "sizeBytes": 1400
  },
  {
    "timestamp": "2025-09-02T17:05:00.132+00:00",
    "sourceId": 12,
    "sequenceNo": 39222,
    "sizeBytes": 1400
  },
  {
    "timestamp": "2025-09-02T17:05:00.913+00:00",
    "sourceId": 12,
    "sequenceNo": 39223,
    "sizeBytes": 1400
  },
  {
    "timestamp": "2025-09-02T17:05:01.739+00:00",
    "sourceId": 12,
    "sequenceNo": 39224,
    "sizeBytes": 1400
  },
  {
    "timestamp": "2025-09-02T17:05:02.408+00:00",
    "sourceId": 12,
    "sequenceNo": 39225,
    "sizeBytes": 1400
  },
  {
    "timestamp": "2025-09-02T17:05:03.233+00:00",
    "sourceId": 12,
    "sequenceNo": 39226,
    "sizeBytes": 1400
  },
  {
    "timestamp": "2025-09-02T17:05:03.708+00:00",
    "sourceId": 12,
    "sequenceNo": 39227,
    "sizeBytes": 1400
  },
  {
    "timestamp": "2025-09-02T17:05:04.497+00:00",
    "sourceId": 12,
    "sequenceNo": 39228,
    "sizeBytes": 1400
  },
  {
    "timestamp": "2025-09-02T17:05:05.298+00:00",
    "sourceId": 12,
    "sequenceNo": 39229,
    "sizeBytes": 1400
  },
  {
    "timestamp": "2025-09-02T17:05:05.939+00:00",
    "sourceId": 12,
    "sequenceNo": 39230,
    "sizeBytes": 1400
  },
  {
    "timestamp": "2025-09-02T17:05:06.454+00:00",
    "sourceId": 12,
    "sequenceNo": 39231,
    "sizeBytes": 1400
  },
  {
    "timestamp": "2025-09-02T17:05:07.091+00:00",
    "sourceId": 12,
    "sequenceNo": 39232,
    "sizeBytes": 1400
  },
  {
    "timestamp": "2025-09-02T17:05:07.993+00:00",
    "sourceId": 12,
    "sequenceNo": 39233,
    "sizeBytes": 1400
  },
  {
    "timestamp": "2025-09-02T17:05:08.537+00:00",
    "sourceId": 12,
    "sequenceNo": 39234,
    "sizeBytes": 1400
  }
]